begin2018/__init__.py
begin2018/_version.py
begin2018/main.py
begin2018-0.0.2.dist-info/METADATA
begin2018-0.0.2.dist-info/RECORD
begin2018-0.0.2.dist-info/WHEEL
begin2018-0.0.2.dist-info/entry_points.txt
begin2018-0.0.2.dist-info/top_level.txt
