Metadata-Version: 2.1
Name: begin2018
Version: 0.0.2
Summary: My first python package in github and pypi
Home-page: https://github.com/AmaanKarim/begin2018
Author: A. K.
Author-email: 14amaakari@oakspark.redbridge.sch.uk
License: Unlicense
Download-URL: https://github.com/AmaanKarim/begin2018/archive/0.0.2.tar.gz
Keywords: python
Platform: UNKNOWN
Classifier: Topic :: Software Development :: Libraries
Classifier: Programming Language :: Python
Classifier: Intended Audience :: Developers
Classifier: Programming Language :: Python :: 2.6
Classifier: Programming Language :: Python :: 2.7
Classifier: Programming Language :: Python :: 3.3
Classifier: Programming Language :: Python :: 3.4
Classifier: Programming Language :: Python :: 3.5
Classifier: Programming Language :: Python :: 3.6
